{
  "meta": {
    "scope": "congressional",
    "contest_type": "agriculture_commissioner",
    "year": 2014,
    "source": "VEST precinct shapefile allocation",
    "allocation_method": "spatial",
    "allocation_source": "spatial:fl_congressional_districts.geojson",
    "match_coverage_pct": 100.0,
    "generated_at_utc": "2026-03-04T00:33:07.982396+00:00"
  },
  "general": {
    "results": {
      "1": {
        "dem_votes": 58347,
        "rep_votes": 160377,
        "other_votes": 375,
        "total_votes": 219099,
        "margin": 102030,
        "margin_pct": 46.56799,
        "winner": "REP",
        "dem_candidate": "Thaddeus Hamilton",
        "rep_candidate": "Adam Putnam",
        "color": "#67000d"
      },
      "10": {
        "dem_votes": 86493,
        "rep_votes": 77400,
        "other_votes": 333,
        "total_votes": 164226,
        "margin": -9093,
        "margin_pct": -5.536882,
        "winner": "DEM",
        "dem_candidate": "Thaddeus Hamilton",
        "rep_candidate": "Adam Putnam",
        "color": "#9ecae1"
      },
      "11": {
        "dem_votes": 67768,
        "rep_votes": 138961,
        "other_votes": 141,
        "total_votes": 206870,
        "margin": 71193,
        "margin_pct": 34.414367,
        "winner": "REP",
        "dem_candidate": "Thaddeus Hamilton",
        "rep_candidate": "Adam Putnam",
        "color": "#a50f15"
      },
      "12": {
        "dem_votes": 78215,
        "rep_votes": 162204,
        "other_votes": 383,
        "total_votes": 240802,
        "margin": 83989,
        "margin_pct": 34.878863,
        "winner": "REP",
        "dem_candidate": "Thaddeus Hamilton",
        "rep_candidate": "Adam Putnam",
        "color": "#a50f15"
      },
      "13": {
        "dem_votes": 102396,
        "rep_votes": 172291,
        "other_votes": 413,
        "total_votes": 275100,
        "margin": 69895,
        "margin_pct": 25.407125,
        "winner": "REP",
        "dem_candidate": "Thaddeus Hamilton",
        "rep_candidate": "Adam Putnam",
        "color": "#cb181d"
      },
      "14": {
        "dem_votes": 98212,
        "rep_votes": 109310,
        "other_votes": 362,
        "total_votes": 207884,
        "margin": 11098,
        "margin_pct": 5.338554,
        "winner": "REP",
        "dem_candidate": "Thaddeus Hamilton",
        "rep_candidate": "Adam Putnam",
        "color": "#fcae91"
      },
      "15": {
        "dem_votes": 68042,
        "rep_votes": 126683,
        "other_votes": 313,
        "total_votes": 195038,
        "margin": 58641,
        "margin_pct": 30.066449,
        "winner": "REP",
        "dem_candidate": "Thaddeus Hamilton",
        "rep_candidate": "Adam Putnam",
        "color": "#a50f15"
      },
      "16": {
        "dem_votes": 67588,
        "rep_votes": 134400,
        "other_votes": 231,
        "total_votes": 202219,
        "margin": 66812,
        "margin_pct": 33.039428,
        "winner": "REP",
        "dem_candidate": "Thaddeus Hamilton",
        "rep_candidate": "Adam Putnam",
        "color": "#a50f15"
      },
      "17": {
        "dem_votes": 92333,
        "rep_votes": 153625,
        "other_votes": 366,
        "total_votes": 246324,
        "margin": 61292,
        "margin_pct": 24.882675,
        "winner": "REP",
        "dem_candidate": "Thaddeus Hamilton",
        "rep_candidate": "Adam Putnam",
        "color": "#cb181d"
      },
      "18": {
        "dem_votes": 57971,
        "rep_votes": 141709,
        "other_votes": 240,
        "total_votes": 199920,
        "margin": 83738,
        "margin_pct": 41.885754,
        "winner": "REP",
        "dem_candidate": "Thaddeus Hamilton",
        "rep_candidate": "Adam Putnam",
        "color": "#67000d"
      },
      "19": {
        "dem_votes": 72065,
        "rep_votes": 154183,
        "other_votes": 297,
        "total_votes": 226545,
        "margin": 82118,
        "margin_pct": 36.247986,
        "winner": "REP",
        "dem_candidate": "Thaddeus Hamilton",
        "rep_candidate": "Adam Putnam",
        "color": "#a50f15"
      },
      "2": {
        "dem_votes": 105182,
        "rep_votes": 152176,
        "other_votes": 547,
        "total_votes": 257905,
        "margin": 46994,
        "margin_pct": 18.221438,
        "winner": "REP",
        "dem_candidate": "Thaddeus Hamilton",
        "rep_candidate": "Adam Putnam",
        "color": "#ef3b2c"
      },
      "20": {
        "dem_votes": 127380,
        "rep_votes": 38139,
        "other_votes": 366,
        "total_votes": 165885,
        "margin": -89241,
        "margin_pct": -53.796907,
        "winner": "DEM",
        "dem_candidate": "Thaddeus Hamilton",
        "rep_candidate": "Adam Putnam",
        "color": "#08306b"
      },
      "21": {
        "dem_votes": 94955,
        "rep_votes": 140868,
        "other_votes": 351,
        "total_votes": 236174,
        "margin": 45913,
        "margin_pct": 19.440328,
        "winner": "REP",
        "dem_candidate": "Thaddeus Hamilton",
        "rep_candidate": "Adam Putnam",
        "color": "#ef3b2c"
      },
      "22": {
        "dem_votes": 111242,
        "rep_votes": 91271,
        "other_votes": 362,
        "total_votes": 202875,
        "margin": -19971,
        "margin_pct": -9.843993,
        "winner": "DEM",
        "dem_candidate": "Thaddeus Hamilton",
        "rep_candidate": "Adam Putnam",
        "color": "#9ecae1"
      },
      "23": {
        "dem_votes": 101470,
        "rep_votes": 97104,
        "other_votes": 345,
        "total_votes": 198919,
        "margin": -4366,
        "margin_pct": -2.194863,
        "winner": "DEM",
        "dem_candidate": "Thaddeus Hamilton",
        "rep_candidate": "Adam Putnam",
        "color": "#c6dbef"
      },
      "24": {
        "dem_votes": 125134,
        "rep_votes": 31860,
        "other_votes": 252,
        "total_votes": 157246,
        "margin": -93274,
        "margin_pct": -59.317248,
        "winner": "DEM",
        "dem_candidate": "Thaddeus Hamilton",
        "rep_candidate": "Adam Putnam",
        "color": "#08306b"
      },
      "25": {
        "dem_votes": 100280,
        "rep_votes": 70541,
        "other_votes": 357,
        "total_votes": 171178,
        "margin": -29739,
        "margin_pct": -17.373144,
        "winner": "DEM",
        "dem_candidate": "Thaddeus Hamilton",
        "rep_candidate": "Adam Putnam",
        "color": "#6baed6"
      },
      "26": {
        "dem_votes": 46753,
        "rep_votes": 77857,
        "other_votes": 196,
        "total_votes": 124806,
        "margin": 31104,
        "margin_pct": 24.921879,
        "winner": "REP",
        "dem_candidate": "Thaddeus Hamilton",
        "rep_candidate": "Adam Putnam",
        "color": "#cb181d"
      },
      "27": {
        "dem_votes": 70988,
        "rep_votes": 88958,
        "other_votes": 289,
        "total_votes": 160235,
        "margin": 17970,
        "margin_pct": 11.214778,
        "winner": "REP",
        "dem_candidate": "Thaddeus Hamilton",
        "rep_candidate": "Adam Putnam",
        "color": "#ef3b2c"
      },
      "28": {
        "dem_votes": 61756,
        "rep_votes": 72552,
        "other_votes": 285,
        "total_votes": 134593,
        "margin": 10796,
        "margin_pct": 8.02122,
        "winner": "REP",
        "dem_candidate": "Thaddeus Hamilton",
        "rep_candidate": "Adam Putnam",
        "color": "#fb6a4a"
      },
      "3": {
        "dem_votes": 83295,
        "rep_votes": 135938,
        "other_votes": 389,
        "total_votes": 219622,
        "margin": 52643,
        "margin_pct": 23.969821,
        "winner": "REP",
        "dem_candidate": "Thaddeus Hamilton",
        "rep_candidate": "Adam Putnam",
        "color": "#cb181d"
      },
      "4": {
        "dem_votes": 85996,
        "rep_votes": 128045,
        "other_votes": 350,
        "total_votes": 214391,
        "margin": 42049,
        "margin_pct": 19.61323,
        "winner": "REP",
        "dem_candidate": "Thaddeus Hamilton",
        "rep_candidate": "Adam Putnam",
        "color": "#ef3b2c"
      },
      "5": {
        "dem_votes": 63155,
        "rep_votes": 144300,
        "other_votes": 375,
        "total_votes": 207830,
        "margin": 81145,
        "margin_pct": 39.04393,
        "winner": "REP",
        "dem_candidate": "Thaddeus Hamilton",
        "rep_candidate": "Adam Putnam",
        "color": "#a50f15"
      },
      "6": {
        "dem_votes": 85046,
        "rep_votes": 155835,
        "other_votes": 299,
        "total_votes": 241180,
        "margin": 70789,
        "margin_pct": 29.351107,
        "winner": "REP",
        "dem_candidate": "Thaddeus Hamilton",
        "rep_candidate": "Adam Putnam",
        "color": "#cb181d"
      },
      "7": {
        "dem_votes": 85388,
        "rep_votes": 144592,
        "other_votes": 394,
        "total_votes": 230374,
        "margin": 59204,
        "margin_pct": 25.699081,
        "winner": "REP",
        "dem_candidate": "Thaddeus Hamilton",
        "rep_candidate": "Adam Putnam",
        "color": "#cb181d"
      },
      "8": {
        "dem_votes": 95656,
        "rep_votes": 170059,
        "other_votes": 426,
        "total_votes": 266141,
        "margin": 74403,
        "margin_pct": 27.956234,
        "winner": "REP",
        "dem_candidate": "Thaddeus Hamilton",
        "rep_candidate": "Adam Putnam",
        "color": "#cb181d"
      },
      "9": {
        "dem_votes": 63072,
        "rep_votes": 71154,
        "other_votes": 253,
        "total_votes": 134479,
        "margin": 8082,
        "margin_pct": 6.00986,
        "winner": "REP",
        "dem_candidate": "Thaddeus Hamilton",
        "rep_candidate": "Adam Putnam",
        "color": "#fb6a4a"
      }
    }
  }
}
